{
    "logic-states": [
        {
            "type": "library",
            "id": {
                "version": "5.5.13"
            },
            "path": "/etc/httpd/modules/libphp.so",
            "environment": {
                "rel": {
                    "hostname": "prod-web01"
                }
            }
        },
        {
            "type": "library",
            "id": {
                "version": "5.5.13"
            },
            "path": "/etc/httpd/modules/libphp.so",
            "environment": {
                "rel": {
                    "hostname": "stage"
                }
            }
        },
        {
            "type": "library",
            "id": {
                "version": "5.5.13"
            },
            "path": "/etc/httpd/modules/libphp.so",
            "environment": {
                "rel": {
                    "hostname": "qa"
                }
            }
        },
        {
            "type": "library",
            "id": {
                "version": "5.5.13"
            },
            "path": "/etc/httpd/modules/libphp.so",
            "environment": {
                "rel": {
                    "hostname": "dev01"
                }
            }
        },
        {
            "type": "library",
            "id": {
                "version": "5.5.13"
            },
            "path": "/etc/httpd/modules/libphp.so",
            "environment": {
                "rel": {
                    "hostname": "dev02"
                }
            }
        }
    ]
}
